bgheatmaps/__init__.py
bgheatmaps/heatmaps.py
bgheatmaps/planner.py
bgheatmaps/slicer.py
examples/cellfinder_cell_density.py
examples/get_coordiantes.py
examples/heatmap_2d.py
examples/heatmap_3d.py
examples/heatmap_spinal_coord.py
examples/heatmap_zebrafish.py
examples/plan.py
examples/slicer_2D.py
bgheatmap-0.4.0.dist-info/LICENSE
bgheatmap-0.4.0.dist-info/METADATA
bgheatmap-0.4.0.dist-info/WHEEL
bgheatmap-0.4.0.dist-info/top_level.txt
bgheatmap-0.4.0.dist-info/RECORD
