Metadata-Version: 2.1
Name: bgheatmap
Version: 0.4.0
Summary: Brain regions heatmaps in brainrender
Home-page: 
Author: Federico Claudi
Requires-Python: >=3.6
License-File: LICENSE
Requires-Dist: brainrender
Requires-Dist: matplotlib
Requires-Dist: numpy
Requires-Dist: myterial
Requires-Dist: rich
